{
  "base_continuity": {
    "files": {
      "evidence/base-ai-blackout.json": "914cbf991e6715e349a4bdb084c05a735aec7690f6d81db88e7c157d31564426",
      "evidence/base-base-transfer-contract.json": "7d32d67b6575e4d1864fc88fcd785d3dac54759aca873df70f91139d2050e463",
      "evidence/base-crash-matrix.json": "662624e0fab67c66f952e4575b0bb632fff0ada6ebe1b639511f4a334d387885"
    },
    "observations": {
      "evidence/base-ai-blackout.json": {
        "rollback": "PASS",
        "runs": 1
      },
      "evidence/base-base-transfer-contract.json": {
        "rollback": "PASS",
        "runs": 1
      },
      "evidence/base-crash-matrix.json": {
        "rollback": "PASS",
        "runs": 1
      }
    },
    "ordinary_base_live": true,
    "rollback_verified": true
  },
  "checks": [
    {
      "detail": {
        "command": [
          "cargo",
          "test",
          "--locked",
          "-p",
          "noos-weft-compile",
          "--",
          "--test-threads=1"
        ],
        "exit_code": 0,
        "packages": [
          "noos-weft-compile"
        ]
      },
      "name": "claim-specific crate tests",
      "passed": true
    }
  ],
  "claim_fingerprints": {
    "E-WEFT-03": "ec6e84b7aaf67d79fc53db1e6d99320be56021f427aac5e76b2348e341e97275"
  },
  "claims": [
    "E-WEFT-03"
  ],
  "command": [
    "tools/gates/run_implementation_claim.py",
    "--claim",
    "E-WEFT-03"
  ],
  "evidence_sha256": "0177590e1ae03d7e006fb70cb115d20825efade4bbacbb23825d7559afa9c4bf",
  "expected_result": "IMPLEMENTED",
  "gate": "implementation-e-weft-03",
  "limitations": [
    "This is local implementation evidence, not independent or production evidence."
  ],
  "registry_schema_version": "1.2.0",
  "result": "IMPLEMENTED",
  "schema_version": "noos.experimental-evidence.v1",
  "source_sha256": {
    "crates/noos-weft-compile/Cargo.toml": "3a98d2a6f7ed8a8b7f5b61abfc5bb9ed4dcaf70249ade80a417f27ff93d93fbd",
    "crates/noos-weft-compile/src/lib.rs": "88a5ff45ed27ee6a887204acaca610f14778bf6b401a3e9a909b4b99d1b19d60"
  }
}
