{
  "base_continuity": {
    "files": {
      "evidence/base-ai-blackout.json": "914cbf991e6715e349a4bdb084c05a735aec7690f6d81db88e7c157d31564426",
      "evidence/base-base-transfer-contract.json": "7d32d67b6575e4d1864fc88fcd785d3dac54759aca873df70f91139d2050e463",
      "evidence/base-crash-matrix.json": "662624e0fab67c66f952e4575b0bb632fff0ada6ebe1b639511f4a334d387885"
    },
    "observations": {
      "evidence/base-ai-blackout.json": {
        "rollback": "PASS",
        "runs": 1
      },
      "evidence/base-base-transfer-contract.json": {
        "rollback": "PASS",
        "runs": 1
      },
      "evidence/base-crash-matrix.json": {
        "rollback": "PASS",
        "runs": 1
      }
    },
    "ordinary_base_live": true,
    "rollback_verified": true
  },
  "checks": [
    {
      "detail": {
        "command": [
          "cargo",
          "test",
          "--locked",
          "-p",
          "noos-commerce",
          "--",
          "--test-threads=1"
        ],
        "exit_code": 0,
        "packages": [
          "noos-commerce"
        ]
      },
      "name": "claim-specific deterministic falsifier tests",
      "passed": true
    }
  ],
  "claim_fingerprints": {
    "S-COMMERCE": "fd93e15107d07e47255fe26570fbbb28b669b14424ebf74d9ca53065a0a00d52"
  },
  "claims": [
    "S-COMMERCE"
  ],
  "command": [
    "tools/gates/run_agent_commerce_claim.py",
    "--claim",
    "S-COMMERCE"
  ],
  "evidence_sha256": "b482cee9471e160f151f7c6a60d9b59762885482d2f2bc84427c053f72728283",
  "expected_result": "IMPLEMENTED",
  "gate": "implementation-s-commerce",
  "limitations": [
    "This is deterministic local implementation evidence, not independent or production evidence."
  ],
  "registry_schema_version": "1.2.0",
  "result": "IMPLEMENTED",
  "schema_version": "noos.experimental-evidence.v1",
  "source_sha256": {
    "crates/noos-commerce/Cargo.toml": "32d97cfaa3a87a46973d349affcb12768befdab82f91ca986cf149c0b2c51297",
    "crates/noos-commerce/src/lib.rs": "503983551931c9def252a5e384bfae72fb739ebd5c056f33ee408d5fad95f6ab",
    "tools/gates/run_agent_commerce_claim.py": "6b30a65cf8288e30fb39d11b41ac0ea81e8b1c22ae653d1c06a62e35e1094b7b"
  }
}
